optimuslib/__init__.py
optimuslib/optimuslib.py
optimuslib-0.0.47.dist-info/METADATA
optimuslib-0.0.47.dist-info/WHEEL
optimuslib-0.0.47.dist-info/RECORD
