Metadata-Version: 2.4
Name: optimuslib
Version: 0.0.47
Summary: Function Library for mostly used codes
Author: Shomi Nanwani
Requires-Python: >=3.9,<4.0
Classifier: Programming Language :: Python :: 3
Classifier: Programming Language :: Python :: 3.9
Classifier: Programming Language :: Python :: 3.10
Classifier: Programming Language :: Python :: 3.11
Classifier: Programming Language :: Python :: 3.12
Classifier: Programming Language :: Python :: 3.13
Classifier: Programming Language :: Python :: 3.14
Requires-Dist: pillow (==9.5.0)
Requires-Dist: pyperclip (>=1.8.2,<2.0.0)
Requires-Dist: requests (>=2.31.0,<3.0.0)
Requires-Dist: requests-futures (>=1.0.0,<2.0.0)
